{
  "created_at": "2026-04-03 07:54:51",
  "experiment_id": "E12",
  "family": "representacion_enriquecida",
  "horizon_results": [
    {
      "comentarios": "E12 representacion expanded | rep_features=25 | source_runs=E1_v5_clean,E5_v4_clean,E3_v2_clean,E7_v3_clean",
      "dataset_periodo": "2024-10-14 a 2026-03-02",
      "deteccion_caidas": 0.8571428571428571,
      "direccion_accuracy": 0.7857142857142857,
      "estado": "corrido",
      "horizonte_sem": 1,
      "l_num": 0.19659292252775692,
      "l_risk": 0.1428571428571429,
      "l_tol": 0.8571428571428571,
      "l_trend": 0.2142857142857143,
      "loss_h": 0.07314225686541448,
      "mae": 0.11863569024802444,
      "notas_config": "{\"feature_candidates\": 83, \"feature_mode\": \"corr\", \"horizon\": 1, \"initial_train_size\": 12, \"lags\": [1, 2, 3, 4, 5, 6], \"model\": \"ridge_representacion\", \"model_params\": {\"alpha_grid\": [0.0001, 0.0001603718743751331, 0.00025719138090593444, 0.0004124626382901352, 0.0006614740641230146, 0.0010608183551394483, 0.0017012542798525892, 0.0027283333764867696, 0.004375479375074184, 0.007017038286703823, 0.011253355826007646, 0.018047217668271703, 0.028942661247167517, 0.046415888336127774, 0.07443803013251689, 0.11937766417144358, 0.19144819761699575, 0.30702906297578497, 0.49238826317067363, 0.7896522868499725, 1.266380173467402, 2.030917620904735, 3.257020655659783, 5.2233450742668435, 8.376776400682925, 13.433993325988988, 21.54434690031882, 34.55107294592218, 55.41020330009492, 88.86238162743408, 142.51026703029962, 228.54638641349882, 366.5241237079626, 587.8016072274912, 942.6684551178854, 1511.77507061566, 2424.462017082326, 3888.155180308085, 6235.507341273912, 10000.0], \"alpha_selection_metric\": \"mae\", \"base_feature_candidates\": 83, \"description\": \"bloque ampliado con diversidad de bases heterogeneas + agregados de desacuerdo + regimen observable\", \"inner_splits\": 3, \"representation_feature_count\": 25, \"representation_features\": [\"rep_pred_e1_v5_clean\", \"rep_pred_e5_v4_clean\", \"rep_pred_e3_v2_clean\", \"rep_pred_e7_v3_clean\", \"rep_delta_e1_v5_clean\", \"rep_delta_e5_v4_clean\", \"rep_delta_e3_v2_clean\", \"rep_delta_e7_v3_clean\", \"rep_pred_mean_all\", \"rep_pred_std_all\", \"rep_pred_range_all\", \"rep_delta_mean_all\", \"rep_delta_std_all\", \"rep_fall_share_all\", \"rep_direction_consensus_mean\", \"rep_pred_mean_nonlinear_tabular\", \"rep_spread_linear_vs_nonlinear\", \"rep_spread_temporal_vs_tabular\", \"reg_obs_delta_lag1\", \"reg_obs_delta_lag2\", \"reg_obs_delta_lag3\", \"reg_obs_delta_mean_w3\", \"reg_obs_abs_delta_mean_w3\", \"reg_obs_delta_std_w3\", \"reg_obs_streak_signed_w3\"], \"representation_mode\": \"expanded\", \"representation_run_ids_override\": [], \"rows_after_dropna\": 26, \"rows_before_dropna\": 73, \"rows_removed\": 47, \"source_run_ids\": [\"E1_v5_clean\", \"E5_v4_clean\", \"E3_v2_clean\", \"E7_v3_clean\"], \"source_run_metadata\": [{\"pred_column\": \"rep_pred_e1_v5_clean\", \"prediction_path\": \"/home/emilio/Documentos/RAdAR/Experimentos/runs/E1_v5_clean_20260321_105449/predicciones_h1.csv\", \"run_dir\": \"/home/emilio/Documentos/RAdAR/Experimentos/runs/E1_v5_clean_20260321_105449\", \"run_id\": \"E1_v5_clean\"}, {\"pred_column\": \"rep_pred_e5_v4_clean\", \"prediction_path\": \"/home/emilio/Documentos/RAdAR/Experimentos/runs/E5_v4_clean_20260330_091736/predicciones_h1.csv\", \"run_dir\": \"/home/emilio/Documentos/RAdAR/Experimentos/runs/E5_v4_clean_20260330_091736\", \"run_id\": \"E5_v4_clean\"}, {\"pred_column\": \"rep_pred_e3_v2_clean\", \"prediction_path\": \"/home/emilio/Documentos/RAdAR/Experimentos/runs/E3_v2_clean_20260325_045918/predicciones_h1.csv\", \"run_dir\": \"/home/emilio/Documentos/RAdAR/Experimentos/runs/E3_v2_clean_20260325_045918\", \"run_id\": \"E3_v2_clean\"}, {\"pred_column\": \"rep_pred_e7_v3_clean\", \"prediction_path\": \"/home/emilio/Documentos/RAdAR/Experimentos/runs/E7_v3_clean_20260330_113801/predicciones_h1.csv\", \"run_dir\": \"/home/emilio/Documentos/RAdAR/Experimentos/runs/E7_v3_clean_20260330_113801\", \"run_id\": \"E7_v3_clean\"}], \"transform_mode\": \"standard\", \"winsor_lower_quantile\": 0.05, \"winsor_upper_quantile\": 0.95}, \"rows_eval\": 14, \"rows_modeling\": 26, \"selected_feature_count_avg\": 30.0, \"target_mode\": \"nivel\", \"transform_mode\": \"standard\"}",
      "rmse": 0.16136509824098674,
      "seleccion_variables": "corr",
      "target": "nivel",
      "transformacion": "standard_scaler",
      "validacion": "walk-forward_expanding",
      "variables_tematicas": "sentimiento_medios, v5_agua_neto, v5_alumbrado_neto, v5_americo_neto, v5_basura_neto, v5_corrupcion_neto, v5_delitos_neto, v5_morena_neto, v5_obras_neto, v5_prevencion_neto, v5_vialidad_neto",
      "variables_temporales": "y_t + lags [1, 2, 3, 4, 5, 6] + representacion_archivada_h1"
    },
    {
      "comentarios": "E12 representacion expanded | rep_features=25 | source_runs=E1_v5_clean,E5_v4_clean,E3_v2_clean,E7_v3_clean",
      "dataset_periodo": "2024-10-14 a 2026-03-02",
      "deteccion_caidas": 0.8333333333333334,
      "direccion_accuracy": 0.7692307692307693,
      "estado": "corrido",
      "horizonte_sem": 2,
      "l_num": 0.19628361147700135,
      "l_risk": 0.16666666666666663,
      "l_tol": 0.7692307692307693,
      "l_trend": 0.23076923076923073,
      "loss_h": 0.06124532882475043,
      "mae": 0.11844903383366369,
      "notas_config": "{\"feature_candidates\": 83, \"feature_mode\": \"corr\", \"horizon\": 2, \"initial_train_size\": 12, \"lags\": [1, 2, 3, 4, 5, 6], \"model\": \"ridge_representacion\", \"model_params\": {\"alpha_grid\": [0.0001, 0.0001603718743751331, 0.00025719138090593444, 0.0004124626382901352, 0.0006614740641230146, 0.0010608183551394483, 0.0017012542798525892, 0.0027283333764867696, 0.004375479375074184, 0.007017038286703823, 0.011253355826007646, 0.018047217668271703, 0.028942661247167517, 0.046415888336127774, 0.07443803013251689, 0.11937766417144358, 0.19144819761699575, 0.30702906297578497, 0.49238826317067363, 0.7896522868499725, 1.266380173467402, 2.030917620904735, 3.257020655659783, 5.2233450742668435, 8.376776400682925, 13.433993325988988, 21.54434690031882, 34.55107294592218, 55.41020330009492, 88.86238162743408, 142.51026703029962, 228.54638641349882, 366.5241237079626, 587.8016072274912, 942.6684551178854, 1511.77507061566, 2424.462017082326, 3888.155180308085, 6235.507341273912, 10000.0], \"alpha_selection_metric\": \"mae\", \"base_feature_candidates\": 83, \"description\": \"bloque ampliado con diversidad de bases heterogeneas + agregados de desacuerdo + regimen observable\", \"inner_splits\": 3, \"representation_feature_count\": 25, \"representation_features\": [\"rep_pred_e1_v5_clean\", \"rep_pred_e5_v4_clean\", \"rep_pred_e3_v2_clean\", \"rep_pred_e7_v3_clean\", \"rep_delta_e1_v5_clean\", \"rep_delta_e5_v4_clean\", \"rep_delta_e3_v2_clean\", \"rep_delta_e7_v3_clean\", \"rep_pred_mean_all\", \"rep_pred_std_all\", \"rep_pred_range_all\", \"rep_delta_mean_all\", \"rep_delta_std_all\", \"rep_fall_share_all\", \"rep_direction_consensus_mean\", \"rep_pred_mean_nonlinear_tabular\", \"rep_spread_linear_vs_nonlinear\", \"rep_spread_temporal_vs_tabular\", \"reg_obs_delta_lag1\", \"reg_obs_delta_lag2\", \"reg_obs_delta_lag3\", \"reg_obs_delta_mean_w3\", \"reg_obs_abs_delta_mean_w3\", \"reg_obs_delta_std_w3\", \"reg_obs_streak_signed_w3\"], \"representation_mode\": \"expanded\", \"representation_run_ids_override\": [], \"rows_after_dropna\": 25, \"rows_before_dropna\": 73, \"rows_removed\": 48, \"source_run_ids\": [\"E1_v5_clean\", \"E5_v4_clean\", \"E3_v2_clean\", \"E7_v3_clean\"], \"source_run_metadata\": [{\"pred_column\": \"rep_pred_e1_v5_clean\", \"prediction_path\": \"/home/emilio/Documentos/RAdAR/Experimentos/runs/E1_v5_clean_20260321_105449/predicciones_h2.csv\", \"run_dir\": \"/home/emilio/Documentos/RAdAR/Experimentos/runs/E1_v5_clean_20260321_105449\", \"run_id\": \"E1_v5_clean\"}, {\"pred_column\": \"rep_pred_e5_v4_clean\", \"prediction_path\": \"/home/emilio/Documentos/RAdAR/Experimentos/runs/E5_v4_clean_20260330_091736/predicciones_h2.csv\", \"run_dir\": \"/home/emilio/Documentos/RAdAR/Experimentos/runs/E5_v4_clean_20260330_091736\", \"run_id\": \"E5_v4_clean\"}, {\"pred_column\": \"rep_pred_e3_v2_clean\", \"prediction_path\": \"/home/emilio/Documentos/RAdAR/Experimentos/runs/E3_v2_clean_20260325_045918/predicciones_h2.csv\", \"run_dir\": \"/home/emilio/Documentos/RAdAR/Experimentos/runs/E3_v2_clean_20260325_045918\", \"run_id\": \"E3_v2_clean\"}, {\"pred_column\": \"rep_pred_e7_v3_clean\", \"prediction_path\": \"/home/emilio/Documentos/RAdAR/Experimentos/runs/E7_v3_clean_20260330_113801/predicciones_h2.csv\", \"run_dir\": \"/home/emilio/Documentos/RAdAR/Experimentos/runs/E7_v3_clean_20260330_113801\", \"run_id\": \"E7_v3_clean\"}], \"transform_mode\": \"standard\", \"winsor_lower_quantile\": 0.05, \"winsor_upper_quantile\": 0.95}, \"rows_eval\": 13, \"rows_modeling\": 25, \"selected_feature_count_avg\": 30.0, \"target_mode\": \"nivel\", \"transform_mode\": \"standard\"}",
      "rmse": 0.1621171834073455,
      "seleccion_variables": "corr",
      "target": "nivel",
      "transformacion": "standard_scaler",
      "validacion": "walk-forward_expanding",
      "variables_tematicas": "sentimiento_medios, v5_agua_neto, v5_alumbrado_neto, v5_americo_neto, v5_basura_neto, v5_corrupcion_neto, v5_delitos_neto, v5_morena_neto, v5_obras_neto, v5_prevencion_neto, v5_vialidad_neto",
      "variables_temporales": "y_t + lags [1, 2, 3, 4, 5, 6] + representacion_archivada_h2"
    },
    {
      "comentarios": "E12 representacion expanded | rep_features=25 | source_runs=E1_v5_clean,E5_v4_clean,E3_v2_clean,E7_v3_clean",
      "dataset_periodo": "2024-10-14 a 2026-03-02",
      "deteccion_caidas": 1.0,
      "direccion_accuracy": 0.8333333333333334,
      "estado": "corrido",
      "horizonte_sem": 3,
      "l_num": 0.2404256022906947,
      "l_risk": 0.0,
      "l_tol": 0.8333333333333334,
      "l_trend": 0.16666666666666663,
      "loss_h": 0.06274468824052294,
      "mae": 0.14508689791223997,
      "notas_config": "{\"feature_candidates\": 83, \"feature_mode\": \"corr\", \"horizon\": 3, \"initial_train_size\": 12, \"lags\": [1, 2, 3, 4, 5, 6], \"model\": \"ridge_representacion\", \"model_params\": {\"alpha_grid\": [0.0001, 0.0001603718743751331, 0.00025719138090593444, 0.0004124626382901352, 0.0006614740641230146, 0.0010608183551394483, 0.0017012542798525892, 0.0027283333764867696, 0.004375479375074184, 0.007017038286703823, 0.011253355826007646, 0.018047217668271703, 0.028942661247167517, 0.046415888336127774, 0.07443803013251689, 0.11937766417144358, 0.19144819761699575, 0.30702906297578497, 0.49238826317067363, 0.7896522868499725, 1.266380173467402, 2.030917620904735, 3.257020655659783, 5.2233450742668435, 8.376776400682925, 13.433993325988988, 21.54434690031882, 34.55107294592218, 55.41020330009492, 88.86238162743408, 142.51026703029962, 228.54638641349882, 366.5241237079626, 587.8016072274912, 942.6684551178854, 1511.77507061566, 2424.462017082326, 3888.155180308085, 6235.507341273912, 10000.0], \"alpha_selection_metric\": \"mae\", \"base_feature_candidates\": 83, \"description\": \"bloque ampliado con diversidad de bases heterogeneas + agregados de desacuerdo + regimen observable\", \"inner_splits\": 3, \"representation_feature_count\": 25, \"representation_features\": [\"rep_pred_e1_v5_clean\", \"rep_pred_e5_v4_clean\", \"rep_pred_e3_v2_clean\", \"rep_pred_e7_v3_clean\", \"rep_delta_e1_v5_clean\", \"rep_delta_e5_v4_clean\", \"rep_delta_e3_v2_clean\", \"rep_delta_e7_v3_clean\", \"rep_pred_mean_all\", \"rep_pred_std_all\", \"rep_pred_range_all\", \"rep_delta_mean_all\", \"rep_delta_std_all\", \"rep_fall_share_all\", \"rep_direction_consensus_mean\", \"rep_pred_mean_nonlinear_tabular\", \"rep_spread_linear_vs_nonlinear\", \"rep_spread_temporal_vs_tabular\", \"reg_obs_delta_lag1\", \"reg_obs_delta_lag2\", \"reg_obs_delta_lag3\", \"reg_obs_delta_mean_w3\", \"reg_obs_abs_delta_mean_w3\", \"reg_obs_delta_std_w3\", \"reg_obs_streak_signed_w3\"], \"representation_mode\": \"expanded\", \"representation_run_ids_override\": [], \"rows_after_dropna\": 24, \"rows_before_dropna\": 73, \"rows_removed\": 49, \"source_run_ids\": [\"E1_v5_clean\", \"E5_v4_clean\", \"E3_v2_clean\", \"E7_v3_clean\"], \"source_run_metadata\": [{\"pred_column\": \"rep_pred_e1_v5_clean\", \"prediction_path\": \"/home/emilio/Documentos/RAdAR/Experimentos/runs/E1_v5_clean_20260321_105449/predicciones_h3.csv\", \"run_dir\": \"/home/emilio/Documentos/RAdAR/Experimentos/runs/E1_v5_clean_20260321_105449\", \"run_id\": \"E1_v5_clean\"}, {\"pred_column\": \"rep_pred_e5_v4_clean\", \"prediction_path\": \"/home/emilio/Documentos/RAdAR/Experimentos/runs/E5_v4_clean_20260330_091736/predicciones_h3.csv\", \"run_dir\": \"/home/emilio/Documentos/RAdAR/Experimentos/runs/E5_v4_clean_20260330_091736\", \"run_id\": \"E5_v4_clean\"}, {\"pred_column\": \"rep_pred_e3_v2_clean\", \"prediction_path\": \"/home/emilio/Documentos/RAdAR/Experimentos/runs/E3_v2_clean_20260325_045918/predicciones_h3.csv\", \"run_dir\": \"/home/emilio/Documentos/RAdAR/Experimentos/runs/E3_v2_clean_20260325_045918\", \"run_id\": \"E3_v2_clean\"}, {\"pred_column\": \"rep_pred_e7_v3_clean\", \"prediction_path\": \"/home/emilio/Documentos/RAdAR/Experimentos/runs/E7_v3_clean_20260330_113801/predicciones_h3.csv\", \"run_dir\": \"/home/emilio/Documentos/RAdAR/Experimentos/runs/E7_v3_clean_20260330_113801\", \"run_id\": \"E7_v3_clean\"}], \"transform_mode\": \"standard\", \"winsor_lower_quantile\": 0.05, \"winsor_upper_quantile\": 0.95}, \"rows_eval\": 12, \"rows_modeling\": 24, \"selected_feature_count_avg\": 30.0, \"target_mode\": \"nivel\", \"transform_mode\": \"standard\"}",
      "rmse": 0.1875489419872445,
      "seleccion_variables": "corr",
      "target": "nivel",
      "transformacion": "standard_scaler",
      "validacion": "walk-forward_expanding",
      "variables_tematicas": "sentimiento_medios, v5_agua_neto, v5_alumbrado_neto, v5_americo_neto, v5_basura_neto, v5_corrupcion_neto, v5_delitos_neto, v5_morena_neto, v5_obras_neto, v5_prevencion_neto, v5_vialidad_neto",
      "variables_temporales": "y_t + lags [1, 2, 3, 4, 5, 6] + representacion_archivada_h3"
    },
    {
      "comentarios": "E12 representacion expanded | rep_features=25 | source_runs=E1_v5_clean,E5_v4_clean,E3_v2_clean,E7_v3_clean",
      "dataset_periodo": "2024-10-14 a 2026-03-02",
      "deteccion_caidas": 0.5,
      "direccion_accuracy": 0.6363636363636364,
      "estado": "corrido",
      "horizonte_sem": 4,
      "l_num": 0.21250025490638935,
      "l_risk": 0.5,
      "l_tol": 0.8181818181818182,
      "l_trend": 0.36363636363636365,
      "loss_h": 0.055815354291676354,
      "mae": 0.12823510681134123,
      "notas_config": "{\"feature_candidates\": 83, \"feature_mode\": \"corr\", \"horizon\": 4, \"initial_train_size\": 12, \"lags\": [1, 2, 3, 4, 5, 6], \"model\": \"ridge_representacion\", \"model_params\": {\"alpha_grid\": [0.0001, 0.0001603718743751331, 0.00025719138090593444, 0.0004124626382901352, 0.0006614740641230146, 0.0010608183551394483, 0.0017012542798525892, 0.0027283333764867696, 0.004375479375074184, 0.007017038286703823, 0.011253355826007646, 0.018047217668271703, 0.028942661247167517, 0.046415888336127774, 0.07443803013251689, 0.11937766417144358, 0.19144819761699575, 0.30702906297578497, 0.49238826317067363, 0.7896522868499725, 1.266380173467402, 2.030917620904735, 3.257020655659783, 5.2233450742668435, 8.376776400682925, 13.433993325988988, 21.54434690031882, 34.55107294592218, 55.41020330009492, 88.86238162743408, 142.51026703029962, 228.54638641349882, 366.5241237079626, 587.8016072274912, 942.6684551178854, 1511.77507061566, 2424.462017082326, 3888.155180308085, 6235.507341273912, 10000.0], \"alpha_selection_metric\": \"mae\", \"base_feature_candidates\": 83, \"description\": \"bloque ampliado con diversidad de bases heterogeneas + agregados de desacuerdo + regimen observable\", \"inner_splits\": 3, \"representation_feature_count\": 25, \"representation_features\": [\"rep_pred_e1_v5_clean\", \"rep_pred_e5_v4_clean\", \"rep_pred_e3_v2_clean\", \"rep_pred_e7_v3_clean\", \"rep_delta_e1_v5_clean\", \"rep_delta_e5_v4_clean\", \"rep_delta_e3_v2_clean\", \"rep_delta_e7_v3_clean\", \"rep_pred_mean_all\", \"rep_pred_std_all\", \"rep_pred_range_all\", \"rep_delta_mean_all\", \"rep_delta_std_all\", \"rep_fall_share_all\", \"rep_direction_consensus_mean\", \"rep_pred_mean_nonlinear_tabular\", \"rep_spread_linear_vs_nonlinear\", \"rep_spread_temporal_vs_tabular\", \"reg_obs_delta_lag1\", \"reg_obs_delta_lag2\", \"reg_obs_delta_lag3\", \"reg_obs_delta_mean_w3\", \"reg_obs_abs_delta_mean_w3\", \"reg_obs_delta_std_w3\", \"reg_obs_streak_signed_w3\"], \"representation_mode\": \"expanded\", \"representation_run_ids_override\": [], \"rows_after_dropna\": 23, \"rows_before_dropna\": 73, \"rows_removed\": 50, \"source_run_ids\": [\"E1_v5_clean\", \"E5_v4_clean\", \"E3_v2_clean\", \"E7_v3_clean\"], \"source_run_metadata\": [{\"pred_column\": \"rep_pred_e1_v5_clean\", \"prediction_path\": \"/home/emilio/Documentos/RAdAR/Experimentos/runs/E1_v5_clean_20260321_105449/predicciones_h4.csv\", \"run_dir\": \"/home/emilio/Documentos/RAdAR/Experimentos/runs/E1_v5_clean_20260321_105449\", \"run_id\": \"E1_v5_clean\"}, {\"pred_column\": \"rep_pred_e5_v4_clean\", \"prediction_path\": \"/home/emilio/Documentos/RAdAR/Experimentos/runs/E5_v4_clean_20260330_091736/predicciones_h4.csv\", \"run_dir\": \"/home/emilio/Documentos/RAdAR/Experimentos/runs/E5_v4_clean_20260330_091736\", \"run_id\": \"E5_v4_clean\"}, {\"pred_column\": \"rep_pred_e3_v2_clean\", \"prediction_path\": \"/home/emilio/Documentos/RAdAR/Experimentos/runs/E3_v2_clean_20260325_045918/predicciones_h4.csv\", \"run_dir\": \"/home/emilio/Documentos/RAdAR/Experimentos/runs/E3_v2_clean_20260325_045918\", \"run_id\": \"E3_v2_clean\"}, {\"pred_column\": \"rep_pred_e7_v3_clean\", \"prediction_path\": \"/home/emilio/Documentos/RAdAR/Experimentos/runs/E7_v3_clean_20260330_113801/predicciones_h4.csv\", \"run_dir\": \"/home/emilio/Documentos/RAdAR/Experimentos/runs/E7_v3_clean_20260330_113801\", \"run_id\": \"E7_v3_clean\"}], \"transform_mode\": \"standard\", \"winsor_lower_quantile\": 0.05, \"winsor_upper_quantile\": 0.95}, \"rows_eval\": 11, \"rows_modeling\": 23, \"selected_feature_count_avg\": 30.0, \"target_mode\": \"nivel\", \"transform_mode\": \"standard\"}",
      "rmse": 0.1698197634848001,
      "seleccion_variables": "corr",
      "target": "nivel",
      "transformacion": "standard_scaler",
      "validacion": "walk-forward_expanding",
      "variables_tematicas": "sentimiento_medios, v5_agua_neto, v5_alumbrado_neto, v5_americo_neto, v5_basura_neto, v5_corrupcion_neto, v5_delitos_neto, v5_morena_neto, v5_obras_neto, v5_prevencion_neto, v5_vialidad_neto",
      "variables_temporales": "y_t + lags [1, 2, 3, 4, 5, 6] + representacion_archivada_h4"
    }
  ],
  "model": "ridge_representacion",
  "run_id": "E12_v2_clean",
  "script_path": "/home/emilio/Documentos/RAdAR/Scripts/Modeling/run_e12_representacion.py",
  "snapshot_path": "/home/emilio/Documentos/RAdAR/Experimentos/runs/E12_v2_clean_20260403_075451/scripts/run_e12_representacion.py",
  "task_type": "regresion"
}