[
  {
    "best_alpha_max": 10000.0,
    "best_alpha_mean": 5421.310288322626,
    "best_alpha_median": 3888.155180308085,
    "best_alpha_min": 55.41020330009492,
    "feature_candidates": 59,
    "feature_mode": "all",
    "horizonte_sem": 1,
    "rows_eval": 28,
    "rows_modeling": 68,
    "selected_feature_count_avg": 59.0,
    "selected_feature_count_max": 59,
    "selected_feature_count_min": 59,
    "target_mode": "delta",
    "transform_mode": "standard"
  },
  {
    "best_alpha_max": 366.5241237079626,
    "best_alpha_mean": 134.6266137321316,
    "best_alpha_median": 142.51026703029962,
    "best_alpha_min": 34.55107294592218,
    "feature_candidates": 59,
    "feature_mode": "all",
    "horizonte_sem": 2,
    "rows_eval": 27,
    "rows_modeling": 67,
    "selected_feature_count_avg": 59.0,
    "selected_feature_count_max": 59,
    "selected_feature_count_min": 59,
    "target_mode": "delta",
    "transform_mode": "standard"
  },
  {
    "best_alpha_max": 3888.155180308085,
    "best_alpha_mean": 688.4860620191678,
    "best_alpha_median": 142.51026703029962,
    "best_alpha_min": 88.86238162743408,
    "feature_candidates": 59,
    "feature_mode": "all",
    "horizonte_sem": 3,
    "rows_eval": 26,
    "rows_modeling": 66,
    "selected_feature_count_avg": 59.0,
    "selected_feature_count_max": 59,
    "selected_feature_count_min": 59,
    "target_mode": "delta",
    "transform_mode": "standard"
  },
  {
    "best_alpha_max": 1511.77507061566,
    "best_alpha_mean": 339.24019328957576,
    "best_alpha_median": 88.86238162743408,
    "best_alpha_min": 34.55107294592218,
    "feature_candidates": 59,
    "feature_mode": "all",
    "horizonte_sem": 4,
    "rows_eval": 25,
    "rows_modeling": 65,
    "selected_feature_count_avg": 59.0,
    "selected_feature_count_max": 59,
    "selected_feature_count_min": 59,
    "target_mode": "delta",
    "transform_mode": "standard"
  }
]